shed/__init__.py
shed/__main__.py
shed/_cli.py
shed/_codemods.py
shed/_is_python_file.py
shed/py.typed
shed/_stdlib_module_names/__init__.py
shed/_stdlib_module_names/py38.py
shed/_stdlib_module_names/py39.py
shed-2024.10.1.dist-info/LICENSE
shed-2024.10.1.dist-info/METADATA
shed-2024.10.1.dist-info/WHEEL
shed-2024.10.1.dist-info/entry_points.txt
shed-2024.10.1.dist-info/top_level.txt
shed-2024.10.1.dist-info/RECORD
