Metadata-Version: 2.1
Name: shed
Version: 2024.10.1
Summary: `shed` canonicalises Python code.
Home-page: https://github.com/Zac-HD/shed
Author: Zac Hatfield-Dodds
Author-email: zac@zhd.dev
License: AGPL-3.0
Project-URL: Source, https://github.com/Zac-HD/shed/
Project-URL: Changelog, https://github.com/Zac-HD/shed/blob/master/CHANGELOG.md
Classifier: Development Status :: 4 - Beta
Classifier: License :: OSI Approved :: GNU Affero General Public License v3
Classifier: Programming Language :: Python :: 3 :: Only
Requires-Python: >=3.9
License-File: LICENSE
Requires-Dist: black>=24.1.0
Requires-Dist: com2ann>=0.3.0
Requires-Dist: libcst>=1.1.0
Requires-Dist: pyupgrade>=3.15.0
Requires-Dist: ruff
